faiz/__init__.py
faiz/faiz.py
faiz/jsons/__init__.py
faiz/temp/__init__.py
faiz/utils/Rank.py
faiz/utils/__init__.py
faiz/utils/cdrcon.py
faiz/utils/cursor.py
faiz/utils/functions.py
faiz/utils/git.py
faiz/utils/qr.py
faiz/utils/convert/__init__.py
faiz/utils/convert/convert.py
faiz/utils/convert/html2pdf.py
faiz/utils/convert/img2pdf.py
faiz/utils/convert/pdf2img.py
faiz/utils/convert/pdf2word.py
faiz/utils/convert/utils.py
faiz/utils/convert/vidtomp3.py
faiz/utils/convert/word2pdf.py
faiz/utils/converter/__init__.py
faiz/utils/converter/avif/__init__.py
faiz/utils/converter/avif/avifcon.py
faiz/utils/converter/jpeg/__init__.py
faiz/utils/converter/jpeg/jpegcon.py
faiz/utils/converter/png/__init__.py
faiz/utils/converter/png/pngcon.py
faiz/utils/converter/utils/__init__.py
faiz/utils/converter/utils/checker.py
faiz/utils/converter/utils/summary.py
faiz/utils/converter/webp/__init__.py
faiz/utils/converter/webp/webpcon.py
faiz/utils/count/__init__.py
faiz/utils/count/count.py
faiz/utils/edge/__init__.py
faiz/utils/edge/edge.py
faiz/utils/edge/handler.py
faiz/utils/env/__init__.py
faiz/utils/env/env.py
faiz/utils/find/__init__.py
faiz/utils/find/find.py
faiz/utils/folder/__init__.py
faiz/utils/folder/folder.py
faiz/utils/framework/__init__.py
faiz/utils/framework/laravel.py
faiz/utils/framework/react.py
faiz/utils/pdf/__init__.py
faiz/utils/pdf/compress.py
faiz/utils/pdf/corrupt.py
faiz/utils/pdf/lock.py
faiz/utils/pdf/merge.py
faiz/utils/pdf/pagenum.py
faiz/utils/pdf/pdf.py
faiz/utils/pdf/repair.py
faiz/utils/pdf/rotate.py
faiz/utils/pdf/split.py
faiz/utils/pdf/unlock.py
faiz/utils/pdf/utils.py
faiz/utils/search/__init__.py
faiz/utils/search/search.py
faiz/utils/ssh/__init__.py
faiz/utils/ssh/ssh.py
faiz/utils/zip/__init__.py
faiz/utils/zip/zip.py
faiz-0.1.7.dist-info/licenses/LICENSE
faiz-0.1.7.dist-info/METADATA
faiz-0.1.7.dist-info/WHEEL
faiz-0.1.7.dist-info/entry_points.txt
faiz-0.1.7.dist-info/top_level.txt
faiz-0.1.7.dist-info/RECORD
