Metadata-Version: 2.4
Name: faiz
Version: 0.1.7
Summary: A personal multipurpose command-line tool (env, git, images, etc.)
Author: Faiz Rajput
Author-email: Faiz Rajput <faizrajput1510@gmail.com>
License-Expression: MIT
Project-URL: Homepage, https://pypi.org/project/faiz/
Classifier: Programming Language :: Python :: 3
Classifier: Operating System :: OS Independent
Requires-Python: >=3.6
License-File: LICENSE
Requires-Dist: requests
Requires-Dist: beautifulsoup4
Requires-Dist: python-dotenv
Requires-Dist: pyautogui
Requires-Dist: googlesearch-python
Requires-Dist: dnspython
Requires-Dist: PyPDF2
Requires-Dist: pikepdf
Requires-Dist: pdf2docx
Requires-Dist: pdfkit
Requires-Dist: docx2pdf
Requires-Dist: zipfile36
Requires-Dist: moviepy
Dynamic: author
Dynamic: license-file
Dynamic: requires-python
